hdl/ALU/vsrc/adder.v
module adder (
	input	[4-1:0]	a,
	input	[4-1:0]	b,
	input					cin,
	output					zero,
	output	[4-1:0]	result 
);
	assign result = a + b + {3'b000, cin};
	assign zero = ~(|result);
endmodule

hdl/ALU/vsrc/top.v
module top  (
	input	[4-1:0]	a,
	input	[4-1:0]	b,
	input	[3-1 :0]	op,
	output	[4-1:0]	out
);
	wire	[4-1:0]	result_add;
	wire 	[4-1:0]	result_not;
	wire 	[4-1:0]	result_and;
	wire	[4-1:0]	result_or;
	wire 	[4-1:0]	result_xor;
	wire	[4-1:0]	result_little;
	wire	[4-1:0]	result_equal;
	
	assign result_not = ~a;
	assign result_and = a & b;
	assign result_or  = a | b;
	assign result_xor = a ^ b;
	
	wire 	[4-1:0]	b_;
	wire 	zero;
	wire 	cin;
	assign b_ = (cin == 1) ? ~b : b;

	assign cin = (op == 3'b001 |
				  op == 3'b110 |
				  op == 3'b111) ? 1 : 0;
	adder add(
		.a(a),
		.b(b_),
		.cin(cin),
		.zero(zero),
		.result(result_add)
	);

	assign result_little = (result_add[3] == 1) ? 1 : 0;
	assign result_equal  = (zero == 1) ? 1 : 0;

	assign out = (op == 3'b000 | op == 3'b001) ? result_add :
				 (op == 3'b010)				   ? result_not :
				 (op == 3'b011)				   ? result_and :
				 (op == 3'b100)			   	   ? result_or	:
				 (op == 3'b101)				   ? result_xor :
				 (op == 3'b110)				   ? result_little:
				 (op == 3'b111)				   ? result_equal:
				 4'b0000;
endmodule

hdl/ALU/dump.vcd
$version Generated by VerilatedVcd $end
$timescale 1s $end

 $scope module TOP $end
  $var wire  4 ( a [3:0] $end
  $var wire  4 ) b [3:0] $end
  $var wire  3 * op [2:0] $end
  $var wire  4 + out [3:0] $end
  $scope module top $end
   $var wire  4 ( a [3:0] $end
   $var wire  4 ) b [3:0] $end
   $var wire  4 0 b_ [3:0] $end
   $var wire  1 ' cin $end
   $var wire  3 * op [2:0] $end
   $var wire  4 + out [3:0] $end
   $var wire  4 # result_add [3:0] $end
   $var wire  4 - result_and [3:0] $end
   $var wire  4 % result_equal [3:0] $end
   $var wire  4 $ result_little [3:0] $end
   $var wire  4 , result_not [3:0] $end
   $var wire  4 . result_or [3:0] $end
   $var wire  4 / result_xor [3:0] $end
   $var wire  1 & zero $end
   $scope module add $end
    $var wire  4 ( a [3:0] $end
    $var wire  4 0 b [3:0] $end
    $var wire  1 ' cin $end
    $var wire  4 # result [3:0] $end
    $var wire  1 & zero $end
   $upscope $end
  $upscope $end
 $upscope $end
$enddefinitions $end


#1
b1010 #
b0001 $
b0000 %
0&
0'
b1000 (
b0010 )
b000 *
b1010 +
b0111 ,
b0000 -
b1010 .
b1010 /
b0010 0
#2
b0110 #
b0000 $
1'
b001 *
b0110 +
b1101 0
#3
b1010 #
b0001 $
0'
b010 *
b0111 +
b0010 0
#4
b011 *
b0000 +
#5
b100 *
b1010 +
#6
b101 *
#7
b0110 #
b0000 $
1'
b110 *
b0000 +
b1101 0
#8
b111 *
